[{
  "id": "delta-n6101",
  "name": "Delta N6101",
  "mode": "VFR",
  "mainRowCount": 10,
  "inputValues": {
    "r2c0_b": "MALAQUITE BEACH",
    "r4c0_b": "RIVIERA",
    "r6c0_b": "FALFURRIAS",
    "r8c0_b": "HEBRONVILLE",
    "r10c0_b": "ALICE",
    "r12c0_b": "ORANGE GROVE",
    "r14c0_b": "KCRP",
    "r2c2": "179",
    "r2c3": "16",
    "r4c3": "28.5",
    "r4c2": "252",
    "r6c2": "254",
    "r6c3": "18",
    "r8c2": "276",
    "r8c3": "29",
    "r10c2": "47",
    "r10c3": "42",
    "r14c2": "112",
    "r14c3": "26",
    "r200c0_b": "CRP",
    "r202c0_b": "KCRP",
    "r2c0_a": "CRP156030",
    "r4c0_a": "ALI151029",
    "r6c0_a": "ALI186032",
    "r8c0_a": "ALI228044",
    "r200c2": "318",
    "r200c3": "15",
    "r18c0_b": "KNGP",
    "r12c2": "27",
    "r18c2": "109",
    "r18c3": "12",
    "r12c3": "14.5",
    "r10c0_a": "ALI264003",
    "r12c0_a": "ALI013014",
    "r16c0_b": "T&G",
    "r2c9": "1200",
    "r3c0": "",
    "r4c9": "1100",
    "r6c9": "1200",
    "r8c9": "1600",
    "r10c9": "1600",
    "r14c9": "1600",
    "r12c9": "1300",
    "r18c9": "1600",
    "altroute": "CRP",
    "altalt": "30"
  },
  "clncFields": {
    "ttc": "",
    "fuel": "",
    "dist": "",
    "deltaT": "",
    "oat": "",
    "tasClimb": "",
    "lbsPhClimb": "",
    "tasCruise": "",
    "lbsPhCruise": "",
    "ias": "",
    "climbDir": "",
    "climbVel": "",
    "cruiseDir": "",
    "cruiseVel": "",
    "vfrGsCalc": "210",
    "vfrLbsPh": "530",
    "vfrAtis": "290.9/127.9 (1)",
    "vfrWindAtAlt": "",
    "vfrClnc1a": "",
    "vfrClnc1b": "KNQI APP 119.9  FSS 122.2 (San Angelo)",
    "vfrClnc2a": "",
    "vfrClnc2b": "TW2 DECON 308.2",
    "vfrClnc3a": "",
    "vfrClnc3b": "Houston Center 128.12/350.3",
    "vfrClnc4a": "",
    "vfrClnc4b": "ERAA: 2,100' MSL"
  },
  "routeBadges": {},
  "vfrTng": {
    "r16c0": true
  },
  "vfrApr": {
    "r202c0": true
  },
  "selectedAlt": 3000,
  "depInput": "KNGP",
  "destInput": "KNGP",
  "infoFields": {
    "depElev": "KNGP 19'",
    "clncDel": "314.3 (2)",
    "gndCont": "257.85 /118.7 (3)",
    "tower": "340.2/134.85 (4)",
    "destElev": "KNGP 19'",
    "destApcCont": "348.725/120.9 (6)",
    "destTower": "340.2/134.85 (4)",
    "destGndCont": "257.85 /118.7 (3)",
    "alternate": "KCRP",
    "altElev": "46'",
    "altApcCont": "348.725/120.9 (6)",
    "altTower": "257.8/119.4 (34)",
    "altGndCont": "269.15/121.9 (33)"
  }
},{
  "id": "delta-n3101",
  "name": "Delta N3101",
  "mode": "VFR",
  "mainRowCount": 9,
  "inputValues": {
    "r2c0_b": "RAYMONDVILLE",
    "r4c0_b": "DIAMOND O RANCH",
    "r6c0_b": "HEBRONVILLE",
    "r8c0_b": "BENAVIDES",
    "r10c0_b": "KCRP",
    "r12c0_b": "T&G",
    "r14c0_b": "KNGP",
    "r2c2": "330",
    "r2c3": "16.5",
    "r4c3": "44",
    "r4c2": "285",
    "r6c2": "345",
    "r6c3": "36",
    "r8c2": "35",
    "r8c3": "22",
    "r10c2": "73",
    "r10c3": "50",
    "r14c2": "108",
    "r14c3": "12",
    "r200c0_b": "CRP",
    "r202c0_b": "KCRP",
    "r2c0_a": "HRL329016",
    "r4c0_a": "MFE323037",
    "r6c0_a": "ALI228044",
    "r8c0_a": "ALI241023",
    "r200c2": "318",
    "r200c3": "15",
    "r2c9": "2100",
    "r4c9": "1700",
    "r6c9": "1700",
    "r8c9": "1600",
    "r10c9": "1600",
    "r14c9": "1600",
    "altroute": "CRP",
    "altalt": "30"
  },
  "clncFields": {
    "ttc": "",
    "fuel": "",
    "dist": "",
    "deltaT": "",
    "oat": "",
    "tasClimb": "",
    "lbsPhClimb": "",
    "tasCruise": "",
    "lbsPhCruise": "",
    "ias": "",
    "climbDir": "",
    "climbVel": "",
    "cruiseDir": "",
    "cruiseVel": "",
    "vfrGsCalc": "210",
    "vfrLbsPh": "530",
    "vfrAtis": "124.85",
    "vfrWindAtAlt": "",
    "vfrClnc1a": "",
    "vfrClnc1b": "KNQI APP 119.9  FSS 122.2 (San Angelo)",
    "vfrClnc2a": "",
    "vfrClnc2b": "TW2 DECON 308.2",
    "vfrClnc3a": "",
    "vfrClnc3b": "Houston Center 128.12/350.3",
    "vfrClnc4a": "",
    "vfrClnc4b": "ERAA: 2,600' MSL"
  },
  "routeBadges": {},
  "vfrTng": {
    "r12c0": true
  },
  "vfrApr": {
    "r202c0": true
  },
  "selectedAlt": 3000,
  "depInput": "KHRL",
  "destInput": "KNGP",
  "infoFields": {
    "depElev": "KHRL 36'",
    "clncDel": "",
    "gndCont": "121.7",
    "tower": "317.6/119.3",
    "destElev": "KNGP 19'",
    "destApcCont": "348.725/120.9 (6)",
    "destTower": "340.2/134.85 (4)",
    "destGndCont": "257.85 /118.7 (3)",
    "alternate": "KCRP",
    "altElev": "46'",
    "altApcCont": "348.725/120.9 (6)",
    "altTower": "257.8/119.4 (34)",
    "altGndCont": "269.15/121.9 (33)"
  }
},{
  "id": "delta-i6101",
  "name": "Delta I6101",
  "mode": "IFR",
  "mainRowCount": 9,
  "inputValues": {
    "r200c0_a": "D→",
    "r200c0_b": "CRP",
    "altroute": "CRP",
    "altalt": "40",
    "r2c0_a": "D→",
    "r2c0_b": "CRP",
    "r4c0_a": "D→",
    "r4c0_b": "LAMMR",
    "r6c0_a": "D→",
    "r6c0_b": "ALI",
    "r8c0_a": "KALI",
    "r10c0_a": "D→",
    "r10c0_b": "VICCC",
    "r2c2": "18",
    "r2c3": "8",
    "r4c2": "243",
    "r4c3": "20",
    "r6c2": "243",
    "r6c3": "12",
    "r10c2": "97",
    "r10c3": "43",
    "r2c1": "CRP",
    "r3c0": "115.5",
    "r4c1": "CRP",
    "r5c0": "115.5",
    "r6c1": "ALI",
    "r7c0": "114.5",
    "r10c1": "CRP",
    "r11c0": "115.5",
    "r200c1": "CRP",
    "r201c0": "115.5",
    "r200c2": "324",
    "r200c3": "21"
  },
  "clncFields": {
    "ttc": "1",
    "fuel": "17",
    "dist": "4",
    "deltaT": "10",
    "oat": "-10",
    "tasClimb": "240",
    "lbsPhClimb": "1020",
    "tasCruise": "242",
    "lbsPhCruise": "551",
    "ias": "232",
    "climbDir": "100",
    "climbVel": "10",
    "cruiseDir": "200",
    "cruiseVel": "20",
    "vfrGsCalc": "210",
    "vfrLbsPh": "555",
    "vfrAtis": "126.8 (31)",
    "vfrWindAtAlt": "",
    "vfrClnc1a": "",
    "vfrClnc1b": "KNQI APP 119.9  FSS 122.2 (San Angelo)",
    "vfrClnc2a": "",
    "vfrClnc2b": "TW2 DECON 308.2",
    "vfrClnc3a": "",
    "vfrClnc3b": "Houston Center 128.12/350.3",
    "vfrClnc4a": "",
    "vfrClnc4b": "ERAA:",
    "vfrGs": ""
  },
  "routeBadges": {
    "r8c0": 2
  },
  "vfrTng": {},
  "vfrApr": {},
  "selectedAlt": 4000,
  "depInput": "KCRP",
  "destInput": "KNGP",
  "infoFields": {
    "depElev": "KCRP 46'",
    "clncDel": "118.55 (32)",
    "gndCont": "269.15/121.9 (33)",
    "tower": "257.8/119.4 (34)",
    "destElev": "KNGP 19'",
    "destApcCont": "348.725/120.9 (6)",
    "destTower": "340.2/134.85 (4)",
    "destGndCont": "257.85 /118.7 (3)",
    "alternate": "KCRP",
    "altElev": "46'",
    "altApcCont": "348.725/120.9 (6)",
    "altTower": "257.8/119.4 (34)",
    "altGndCont": "269.15/121.9 (33)"
  }
},{
  "id": "delta-i6102",
  "name": "Delta I6102",
  "mode": "IFR",
  "mainRowCount": 9,
  "inputValues": {
    "r200c0_a": "D→",
    "r200c0_b": "IVOLY",
    "r200c3": "27",
    "r200c2": "170",
    "r2c0_a": "D→",
    "r2c0_b": "PSX",
    "r4c0_a": "D→",
    "r4c0_b": "PSX/275/10",
    "r6c0_a": "KPKV",
    "r8c0_a": "D→",
    "r8c0_b": "VCT",
    "r10c0_a": "KVCT",
    "r2c2": "305",
    "r2c3": "4",
    "r4c2": "275",
    "r4c3": "20",
    "r8c2": "311",
    "r8c3": "22",
    "r202c0_a": "D→",
    "r202c0_b": "CRP",
    "r202c2": "210",
    "r202c3": "42",
    "altroute": "IVOLY CRP",
    "altalt": "30",
    "r2c1": "PSX",
    "r3c0": "117.3",
    "r4c1": "PSX",
    "r5c0": "117.3",
    "r8c1": "VCT",
    "r9c0": "109.0",
    "r200c1": "VCT",
    "r201c0": "109.0",
    "r202c1": "CRP",
    "r203c0": "115.5"
  },
  "clncFields": {
    "ttc": "1",
    "fuel": "13",
    "dist": "3",
    "deltaT": "10",
    "oat": "-10",
    "tasClimb": "180",
    "lbsPhClimb": "780",
    "tasCruise": "242",
    "lbsPhCruise": "569",
    "ias": "236",
    "climbDir": "100",
    "climbVel": "10",
    "cruiseDir": "200",
    "cruiseVel": "20",
    "vfrGsCalc": "210",
    "vfrLbsPh": "555",
    "vfrAtis": "126.8 (31)",
    "vfrWindAtAlt": "",
    "vfrClnc1a": "",
    "vfrClnc1b": "KNQI APP 119.9  FSS 122.2 (San Angelo)",
    "vfrClnc2a": "",
    "vfrClnc2b": "TW2 DECON 308.2",
    "vfrClnc3a": "",
    "vfrClnc3b": "Houston Center 128.12/350.3",
    "vfrClnc4a": "",
    "vfrClnc4b": "ERAA:",
    "vfrGs": ""
  },
  "routeBadges": {
    "r6c0": 1,
    "r10c0": 1,
    "r8c0": "H"
  },
  "vfrTng": {},
  "vfrApr": {},
  "selectedAlt": 3000,
  "depInput": "KPSX",
  "destInput": "KVCT",
  "infoFields": {
    "depElev": "KPSX 14'",
    "clncDel": "",
    "gndCont": "",
    "tower": "122.8 (C)",
    "destElev": "KVCT 115'",
    "destApcCont": "135.05 (22)",
    "destTower": "257.95/126.075 (44)",
    "destGndCont": "239.25/120.525 (43)",
    "alternate": "KCRP",
    "altElev": "46'",
    "altApcCont": "348.725/120.9 (6)",
    "altTower": "257.8/119.4 (34)",
    "altGndCont": "269.15/121.9 (33)"
  }
},{
  "id": "delta-i3101",
  "name": "Delta I3101",
  "mode": "IFR",
  "mainRowCount": 9,
  "inputValues": {
    "r2c0_a": "D→",
    "r2c0_b": "WORRY",
    "r4c0_a": "V13",
    "r4c0_b": "IVOLY",
    "r6c0_a": "V13",
    "r6c0_b": "PSX",
    "r8c0_a": "KPSX",
    "r10c0_a": "D→",
    "r10c0_b": "VCT",
    "r200c0_a": "D→",
    "r200c0_b": "IVOLY",
    "r202c0_a": "V13",
    "r202c0_b": "CRP",
    "r2c2": "001",
    "r2c3": "25",
    "r4c3": "26",
    "r4c2": "030",
    "r6c2": "053",
    "r6c3": "38",
    "r10c2": "283",
    "r10c3": "40",
    "r200c2": "170",
    "r200c3": "27",
    "r202c2": "210",
    "r202c3": "42",
    "altroute": "IVOLY CRP",
    "altalt": "90",
    "r2c1": "CRP",
    "r3c0": "115.5",
    "r4c1": "CRP",
    "r5c0": "115.5",
    "r6c1": "PSX",
    "r7c0": "117.3",
    "r10c1": "VCT",
    "r11c0": "109.0",
    "r200c1": "VCT",
    "r201c0": "109.0",
    "r202c1": "CRP",
    "r203c0": "115.5"
  },
  "clncFields": {
    "ttc": "3",
    "fuel": "38",
    "dist": "9",
    "deltaT": "10",
    "oat": "-10",
    "tasClimb": "180",
    "lbsPhClimb": "760",
    "tasCruise": "242",
    "lbsPhCruise": "471",
    "ias": "212",
    "climbDir": "100",
    "climbVel": "10",
    "cruiseDir": "200",
    "cruiseVel": "20",
    "vfrGsCalc": "210",
    "vfrLbsPh": "555",
    "vfrAtis": "290.9/127.9 (1)",
    "vfrWindAtAlt": "",
    "vfrClnc1a": "",
    "vfrClnc1b": "KNQI APP 119.9  FSS 122.2 (San Angelo)",
    "vfrClnc2a": "",
    "vfrClnc2b": "TW2 DECON 308.2",
    "vfrClnc3a": "",
    "vfrClnc3b": "Houston Center 128.12/350.3",
    "vfrClnc4a": "",
    "vfrClnc4b": "ERAA:",
    "vfrGs": ""
  },
  "routeBadges": {
    "r8c0": 1
  },
  "vfrTng": {},
  "vfrApr": {},
  "selectedAlt": 9000,
  "depInput": "KNGP",
  "destInput": "KVCT",
  "infoFields": {
    "depElev": "KNGP 19'",
    "clncDel": "314.3 (2)",
    "gndCont": "257.85 /118.7 (3)",
    "tower": "340.2/134.85 (4)",
    "destElev": "KVCT 115'",
    "destApcCont": "135.05 (22)",
    "destTower": "257.95/126.075 (44)",
    "destGndCont": "239.25/120.525 (43)",
    "alternate": "KCRP",
    "altElev": "46'",
    "altApcCont": "348.725/120.9 (6)",
    "altTower": "257.8/119.4 (34)",
    "altGndCont": "269.15/121.9 (33)"
  }
},{
  "id": "delta-i3102",
  "name": "Delta I3102",
  "mode": "IFR",
  "mainRowCount": 9,
  "inputValues": {
    "r2c0_a": "D→",
    "r2c0_b": "ROKKI",
    "r4c0_a": "KRKP",
    "r6c0_a": "D→",
    "r6c0_b": "COPAN",
    "r8c0_a": "D→",
    "r8c0_b": "VICCC",
    "r200c0_a": "D→",
    "r200c0_b": "CRP",
    "altroute": "CRP",
    "altalt": "30",
    "r200c2": "324",
    "r200c3": "21",
    "r200c1": "CRP",
    "r201c0": "115.5",
    "r2c1": "CRP",
    "r3c0": "115.5",
    "r6c1": "CRP",
    "r7c0": "115.5",
    "r8c1": "CRP",
    "r9c0": "115.5",
    "r2c2": "028",
    "r2c3": "18",
    "r6c2": "257",
    "r6c3": "8",
    "r8c2": "180",
    "r8c3": "27"
  },
  "clncFields": {
    "ttc": "1",
    "fuel": "13",
    "dist": "3",
    "deltaT": "10",
    "oat": "-10",
    "tasClimb": "180",
    "lbsPhClimb": "780",
    "tasCruise": "242",
    "lbsPhCruise": "569",
    "ias": "236",
    "climbDir": "100",
    "climbVel": "10",
    "cruiseDir": "200",
    "cruiseVel": "20",
    "vfrGsCalc": "210",
    "vfrLbsPh": "555",
    "vfrAtis": "126.8 (31)",
    "vfrWindAtAlt": "",
    "vfrClnc1a": "",
    "vfrClnc1b": "KNQI APP 119.9  FSS 122.2 (San Angelo)",
    "vfrClnc2a": "",
    "vfrClnc2b": "TW2 DECON 308.2",
    "vfrClnc3a": "",
    "vfrClnc3b": "Houston Center 128.12/350.3",
    "vfrClnc4a": "",
    "vfrClnc4b": "ERAA:",
    "vfrGs": ""
  },
  "routeBadges": {
    "r4c0": 1,
    "r6c0": "H"
  },
  "vfrTng": {},
  "vfrApr": {},
  "selectedAlt": 3000,
  "depInput": "KCRP",
  "destInput": "KNGP",
  "infoFields": {
    "depElev": "KCRP 46'",
    "clncDel": "118.55 (32)",
    "gndCont": "269.15/121.9 (33)",
    "tower": "257.8/119.4 (34)",
    "destElev": "KNGP 19'",
    "destApcCont": "348.725/120.9 (6)",
    "destTower": "340.2/134.85 (4)",
    "destGndCont": "257.85 /118.7 (3)",
    "alternate": "KCRP",
    "altElev": "46'",
    "altApcCont": "348.725/120.9 (6)",
    "altTower": "257.8/119.4 (34)",
    "altGndCont": "269.15/121.9 (33)"
  }
},{
  "id": "delta-i3103",
  "name": "Delta I3103",
  "mode": "IFR",
  "mainRowCount": 7,
  "inputValues": {
    "r200c0_a": "D→",
    "r200c0_b": "CRP",
    "r200c3": "0",
    "altalt": "30",
    "altroute": "CRP",
    "r2c0_a": "KNGP",
    "r4c0_a": "D→",
    "r4c0_b": "CRP",
    "r4c2": "324",
    "r4c3": "15",
    "r200c2": "0",
    "r4c1": "CRP",
    "r5c0": "115.5",
    "r200c1": "CRP",
    "r201c0": "115.5"
  },
  "clncFields": {
    "ttc": "1",
    "fuel": "13",
    "dist": "3",
    "deltaT": "10",
    "oat": "-10",
    "tasClimb": "180",
    "lbsPhClimb": "780",
    "tasCruise": "242",
    "lbsPhCruise": "569",
    "ias": "236",
    "climbDir": "100",
    "climbVel": "10",
    "cruiseDir": "200",
    "cruiseVel": "20",
    "vfrGsCalc": "210",
    "vfrLbsPh": "555",
    "vfrAtis": "290.9/127.9 (1)",
    "vfrWindAtAlt": "",
    "vfrClnc1a": "",
    "vfrClnc1b": "KNQI APP 119.9  FSS 122.2 (San Angelo)",
    "vfrClnc2a": "",
    "vfrClnc2b": "TW2 DECON 308.2",
    "vfrClnc3a": "",
    "vfrClnc3b": "Houston Center 128.12/350.3",
    "vfrClnc4a": "",
    "vfrClnc4b": "ERAA:",
    "vfrGs": ""
  },
  "routeBadges": {
    "r2c0": 3,
    "r4c0": "H"
  },
  "vfrTng": {},
  "vfrApr": {},
  "selectedAlt": 3000,
  "depInput": "KNGP",
  "destInput": "KCRP",
  "infoFields": {
    "depElev": "KNGP 19'",
    "clncDel": "314.3 (2)",
    "gndCont": "257.85 /118.7 (3)",
    "tower": "340.2/134.85 (4)",
    "destElev": "KCRP 46'",
    "destApcCont": "348.725/120.9 (6)",
    "destTower": "257.8/119.4 (34)",
    "destGndCont": "269.15/121.9 (33)",
    "alternate": "KNGP",
    "altElev": "19'",
    "altApcCont": "348.725/120.9 (6)",
    "altTower": "340.2/134.85 (4)",
    "altGndCont": "257.85 /118.7 (3)"
  }
},{
  "id": "delta-i3104",
  "name": "Delta I3104",
  "mode": "IFR",
  "mainRowCount": 7,
  "inputValues": {
    "r2c0_a": "D→",
    "r2c0_b": "LOCOE",
    "r4c0_a": "V70",
    "r4c0_b": "JIMIE",
    "r6c0_a": "V20",
    "r6c0_b": "HARGI",
    "r8c0_a": "D→",
    "r8c0_b": "MEKVE",
    "r10c0_a": "KMFE",
    "r200c0_a": "D→",
    "r200c0_b": "MAYRR",
    "r2c2": "213",
    "r2c3": "28",
    "r4c2": "184",
    "r4c3": "34",
    "r6c2": "209",
    "r6c3": "22",
    "r8c2": "209",
    "r8c3": "9",
    "r200c2": "073",
    "r200c3": "18",
    "altalt": "80",
    "altroute": "MAYRR",
    "r2c1": "CRP",
    "r3c0": "115.5",
    "r4c1": "CRP",
    "r5c0": "115.5",
    "r6c1": "MFE",
    "r7c0": "117.2",
    "r8c1": "MFE",
    "r9c0": "117.2"
  },
  "clncFields": {
    "ttc": "3",
    "fuel": "34",
    "dist": "8",
    "deltaT": "10",
    "oat": "-10",
    "tasClimb": "160",
    "lbsPhClimb": "680",
    "tasCruise": "242",
    "lbsPhCruise": "486",
    "ias": "216",
    "climbDir": "100",
    "climbVel": "10",
    "cruiseDir": "200",
    "cruiseVel": "20",
    "vfrGsCalc": "210",
    "vfrLbsPh": "555",
    "vfrAtis": "290.9/127.9 (1)",
    "vfrWindAtAlt": "",
    "vfrClnc1a": "",
    "vfrClnc1b": "KNQI APP 119.9  FSS 122.2 (San Angelo)",
    "vfrClnc2a": "",
    "vfrClnc2b": "TW2 DECON 308.2",
    "vfrClnc3a": "",
    "vfrClnc3b": "Houston Center 128.12/350.3",
    "vfrClnc4a": "",
    "vfrClnc4b": "ERAA:",
    "vfrGs": ""
  },
  "routeBadges": {
    "r10c0": 2
  },
  "vfrTng": {},
  "vfrApr": {},
  "selectedAlt": 8000,
  "depInput": "KNGP",
  "destInput": "KMFE",
  "infoFields": {
    "depElev": "KNGP 19'",
    "clncDel": "314.3 (2)",
    "gndCont": "257.85 /118.7 (3)",
    "tower": "340.2/134.85 (4)",
    "destElev": "KMFE 107'",
    "destApcCont": "377.2/165.55",
    "destTower": "256.9/118.5",
    "destGndCont": "121.8",
    "alternate": "KHRL",
    "altElev": "36'",
    "altApcCont": "279.5/120.7",
    "altTower": "317.6/119.3",
    "altGndCont": "121.7"
  }
},{
  "id": "delta-i6201",
  "name": "Delta I6201",
  "mode": "IFR",
  "mainRowCount": 7,
  "inputValues": {
    "r4c0_a": "D→",
    "r8c0_a": "D→",
    "r10c0_a": "D→",
    "r2c0_a": "KNGP",
    "r4c0_b": "ROKKI",
    "r6c0_a": "KRKP",
    "r8c0_b": "COPAN",
    "r10c0_b": "HADON",
    "r200c0_a": "D→",
    "r200c0_b": "CRP",
    "altroute": "CRP",
    "altalt": "30",
    "r4c2": "352",
    "r4c3": "20",
    "r8c2": "257",
    "r8c3": "8",
    "r10c2": "205",
    "r10c3": "33",
    "r200c2": "358",
    "r200c3": "20",
    "r200c1": "CRP",
    "r201c0": "115.5",
    "r4c1": "CRP",
    "r5c0": "115.5",
    "r8c1": "CRP",
    "r9c0": "115.5",
    "r10c1": "CRP",
    "r11c0": "115.5"
  },
  "clncFields": {
    "ttc": "1",
    "fuel": "13",
    "dist": "3",
    "deltaT": "10",
    "oat": "-10",
    "tasClimb": "180",
    "lbsPhClimb": "780",
    "tasCruise": "242",
    "lbsPhCruise": "569",
    "ias": "236",
    "climbDir": "100",
    "climbVel": "10",
    "cruiseDir": "200",
    "cruiseVel": "20",
    "vfrGsCalc": "210",
    "vfrLbsPh": "555",
    "vfrAtis": "290.9/127.9 (1)",
    "vfrWindAtAlt": "",
    "vfrClnc1a": "",
    "vfrClnc1b": "KNQI APP 119.9  FSS 122.2 (San Angelo)",
    "vfrClnc2a": "",
    "vfrClnc2b": "TW2 DECON 308.2",
    "vfrClnc3a": "",
    "vfrClnc3b": "Houston Center 128.12/350.3",
    "vfrClnc4a": "",
    "vfrClnc4b": "ERAA:",
    "vfrGs": ""
  },
  "routeBadges": {
    "r2c0": 1,
    "r6c0": 1,
    "r8c0": "H"
  },
  "vfrTng": {},
  "vfrApr": {},
  "selectedAlt": 3000,
  "depInput": "KNGP",
  "destInput": "kcrp",
  "infoFields": {
    "depElev": "KNGP 19'",
    "clncDel": "314.3 (2)",
    "gndCont": "257.85 /118.7 (3)",
    "tower": "340.2/134.85 (4)",
    "destElev": "KCRP 46'",
    "destApcCont": "348.725/120.9 (6)",
    "destTower": "257.8/119.4 (34)",
    "destGndCont": "269.15/121.9 (33)",
    "alternate": "KNGP",
    "altElev": "19'",
    "altApcCont": "348.725/120.9 (6)",
    "altTower": "340.2/134.85 (4)",
    "altGndCont": "257.85 /118.7 (3)"
  }
},{
  "id": "delta-i6202",
  "name": "Delta I6202",
  "mode": "IFR",
  "mainRowCount": 7,
  "inputValues": {
    "r200c0_a": "D→",
    "r200c0_b": "CRP",
    "r200c1": "CRP",
    "r201c0": "115.5",
    "r2c0_a": "D→",
    "r2c0_b": "PANTH",
    "r4c0_a": "T69",
    "r6c0_a": "D→",
    "r6c0_b": "CRP",
    "r8c0_a": "KCRP",
    "r6c1": "CRP",
    "r7c0": "115.5",
    "r3c0": "115.5",
    "r2c1": "CRP",
    "altroute": "CRP",
    "altalt": "30",
    "r200c2": "0",
    "r200c3": "0",
    "r6c2": "138",
    "r6c3": "10",
    "r2c2": "343",
    "r2c3": "21"
  },
  "clncFields": {
    "ttc": "1",
    "fuel": "13",
    "dist": "3",
    "deltaT": "10",
    "oat": "-10",
    "tasClimb": "180",
    "lbsPhClimb": "780",
    "tasCruise": "242",
    "lbsPhCruise": "569",
    "ias": "236",
    "climbDir": "100",
    "climbVel": "10",
    "cruiseDir": "200",
    "cruiseVel": "20",
    "vfrGsCalc": "210",
    "vfrLbsPh": "555",
    "vfrAtis": "126.8 (31)",
    "vfrWindAtAlt": "",
    "vfrClnc1a": "",
    "vfrClnc1b": "KNQI APP 119.9  FSS 122.2 (San Angelo)",
    "vfrClnc2a": "",
    "vfrClnc2b": "TW2 DECON 308.2",
    "vfrClnc3a": "",
    "vfrClnc3b": "Houston Center 128.12/350.3",
    "vfrClnc4a": "",
    "vfrClnc4b": "ERAA:",
    "vfrGs": ""
  },
  "routeBadges": {
    "r4c0": 1,
    "r8c0": 1
  },
  "vfrTng": {},
  "vfrApr": {},
  "selectedAlt": 3000,
  "depInput": "KCRP",
  "destInput": "KCRP",
  "infoFields": {
    "depElev": "KCRP 46'",
    "clncDel": "118.55 (32)",
    "gndCont": "269.15/121.9 (33)",
    "tower": "257.8/119.4 (34)",
    "destElev": "KCRP 46'",
    "destApcCont": "348.725/120.9 (6)",
    "destTower": "257.8/119.4 (34)",
    "destGndCont": "269.15/121.9 (33)",
    "alternate": "KNGP",
    "altElev": "19'",
    "altApcCont": "348.725/120.9 (6)",
    "altTower": "340.2/134.85 (4)",
    "altGndCont": "257.85 /118.7 (3)"
  }
},{
  "id": "nubin-13r-loop",
  "name": "NUBIN 1/3R Loop",
  "mode": "IFR",
  "mainRowCount": 9,
  "inputValues": {
    "r2c0_a": "D→",
    "r2c0_b": "WORRY",
    "r4c0_a": "V13",
    "r4c0_b": "BLOKS",
    "r6c0_a": "D→",
    "r6c0_b": "VCT",
    "r8c0_a": "KVCT",
    "r10c0_a": "D→",
    "r10c0_b": "BRASY",
    "r12c0_a": "D→",
    "r12c0_b": "COPAN",
    "r200c0_a": "D→",
    "r200c0_b": "CRP",
    "r2c2": "001",
    "r2c3": "25",
    "r4c2": "030",
    "r4c3": "21",
    "r6c2": "356",
    "r6c3": "31",
    "r10c2": "167",
    "r10c3": "42",
    "r12c2": "252",
    "r12c3": "24",
    "altroute": "CRP",
    "r200c2": "225",
    "r200c3": "16",
    "altalt": "30",
    "r200c1": "CRP",
    "r201c0": "115.5",
    "r2c1": "CRP",
    "r3c0": "115.5",
    "r4c1": "CRP",
    "r5c0": "115.5",
    "r6c1": "VCT",
    "r7c0": "109.0",
    "r10c1": "VCT",
    "r11c0": "109.0",
    "r12c1": "CRP",
    "r13c0": "115.5"
  },
  "clncFields": {
    "ttc": "3",
    "fuel": "30",
    "dist": "7",
    "deltaT": "",
    "oat": "",
    "tasClimb": "140",
    "lbsPhClimb": "600",
    "tasCruise": "241",
    "lbsPhCruise": "499",
    "ias": "222",
    "climbDir": "",
    "climbVel": "",
    "cruiseDir": "",
    "cruiseVel": "",
    "vfrGsCalc": "210",
    "vfrLbsPh": "555",
    "vfrAtis": "290.9/127.9 (1)",
    "vfrWindAtAlt": "",
    "vfrClnc1a": "",
    "vfrClnc1b": "KNQI APP 119.9  FSS 122.2 (San Angelo)",
    "vfrClnc2a": "",
    "vfrClnc2b": "TW2 DECON 308.2",
    "vfrClnc3a": "",
    "vfrClnc3b": "Houston Center 128.12/350.3",
    "vfrClnc4a": "",
    "vfrClnc4b": "ERAA:",
    "vfrGs": ""
  },
  "routeBadges": {
    "r8c0": 2,
    "r12c0": "H"
  },
  "vfrTng": {},
  "vfrApr": {},
  "selectedAlt": 7000,
  "depInput": "KNGP",
  "destInput": "KNGP",
  "infoFields": {
    "depElev": "KNGP 19'",
    "clncDel": "314.3 (2)",
    "gndCont": "257.85 /118.7 (3)",
    "tower": "340.2/134.85 (4)",
    "destElev": "KNGP 19'",
    "destApcCont": "348.725/120.9 (6)",
    "destTower": "340.2/134.85 (4)",
    "destGndCont": "257.85 /118.7 (3)",
    "alternate": "KCRP",
    "altElev": "46'",
    "altApcCont": "348.725/120.9 (6)",
    "altTower": "257.8/119.4 (34)",
    "altGndCont": "269.15/121.9 (33)"
  }
}]
